finding_best_similar/__init__.py
finding_best_similar/__main__.py
finding_best_similar/core.py
finding_best_similar-1.0.0.dist-info/METADATA
finding_best_similar-1.0.0.dist-info/WHEEL
finding_best_similar-1.0.0.dist-info/top_level.txt
finding_best_similar-1.0.0.dist-info/RECORD
