Metadata-Version: 2.4
Name: finding_best_similar
Version: 1.0.0
Summary: Finding Best Similar (FBS) Method
Author: Ali Forouzan, Hadi Sadoghi Yazdi
Author-email: ali.forouzan7@gmail.com
Project-URL: Bug Reports, https://github.com/phoorooz/FBS/issues
Project-URL: Source, https://github.com/phoorooz/FBS
Keywords: Time Series Similarity,Pattern Matching,Information Theory,Elastic Matching,Finding Best Similar
Classifier: Programming Language :: Python :: 3
Classifier: Development Status :: 4 - Beta
Classifier: Intended Audience :: Science/Research
Classifier: License :: OSI Approved :: MIT License
Classifier: Operating System :: OS Independent
Classifier: Topic :: Scientific/Engineering :: Information Analysis
Requires-Python: >=3.9
Requires-Dist: scipy
Requires-Dist: numpy
Requires-Dist: pandas
Requires-Dist: matplotlib
Requires-Dist: tqdm
Dynamic: author
Dynamic: author-email
Dynamic: classifier
Dynamic: keywords
Dynamic: project-url
Dynamic: requires-dist
Dynamic: requires-python
Dynamic: summary
